{"cards": [{"id": 80645, "collectible": 1, "slug": "80645-grave-strength", "classId": 1, "multiClassIds": [], "spellSchoolId": 6, "cardTypeId": 5, "cardSetId": 1637, "rarityId": 4, "artistName": "Thomas Tenery", "manaCost": 4, "name": "Grave Strength", "text": "Give your minions +1 Attack. Spend 5 <b>Corpses</b> to give them +3 instead.", "image": "https://d15f34w2p8l1cc.cloudfront.net/hearthstone/542d9adc47c0a8dc7f30d855660c5b8f06c4fcf5ef70afcf8f62c6a8b7d11129.png", "imageGold": "", "flavorText": "They're just standing there\u2026 MENACINGLY!", "cropImage": "https://d15f34w2p8l1cc.cloudfront.net/hearthstone/71c4c855b08e0d811efd46339ca9d78b20458847c3ee31793c3b26080b318023.png", "keywordIds": [247], "isZilliaxFunctionalModule": false, "isZilliaxCosmeticModule": false, "runeCost": {"blood": 0, "frost": 0, "unholy": 3}}, {"id": 98704, "collectible": 1, "slug": "98704-greedy-partner", "classId": 12, "multiClassIds": [], "cardTypeId": 4, "cardSetId": 1892, "rarityId": 1, "artistName": "Vika Yarova", "health": 3, "attack": 2, "manaCost": 2, "name": "Greedy Partner", "text": "<b>Battlecry:</b> If you're holding another 2-Cost card, get a Coin.", "image": "https://d15f34w2p8l1cc.cloudfront.net/hearthstone/e54556f8d86446bec97848050a7adccc1149b58f80f9f94c3ca6c9fdaa8c41e7.png", "imageGold": "", "flavorText": "\"Don't worry, we'll evenly split the bounty. Then I'll have two evenly sized piles of gold!\"", "cropImage": "https://d15f34w2p8l1cc.cloudfront.net/hearthstone/a51bbd3d37365e173c799df128af60d30f2adb1fa3b3fddb0642ca3a914f2b8e.png", "childIds": [1746], "keywordIds": [8], "isZilliaxFunctionalModule": false, "isZilliaxCosmeticModule": false}, {"id": 111353, "collectible": 1, "slug": "111353-greybough", "classId": 2, "multiClassIds": [], "cardTypeId": 4, "cardSetId": 1637, "rarityId": 5, "artistName": "Steven Prescott", "health": 6, "attack": 4, "manaCost": 5, "name": "Greybough", "text": "<b>Taunt</b> <b>Deathrattle:</b> Give a random friendly minion \"<b>Deathrattle:</b> Summon Greybough.\"", "image": "https://d15f34w2p8l1cc.cloudfront.net/hearthstone/132c04c9762371daac4f14d1c1c2afa2d1bf3f84ad332eafd6d7c6625b074b7d.png", "imageGold": "", "flavorText": "The best time to plant a tree was 20 years ago. The next best time is when you lose a minion.", "cropImage": "https://d15f34w2p8l1cc.cloudfront.net/hearthstone/9a23c7683b2c83ece42366ad22b9fb4f7558dcf33cc5c0d4a9e8f86846ac400a.png", "keywordIds": [1, 12], "copyOfCardId": 61606, "isZilliaxFunctionalModule": false, "isZilliaxCosmeticModule": false}, {"id": 102196, "collectible": 1, "slug": "102196-grimestreet-outfitter", "classId": 5, "multiClassIds": [], "cardTypeId": 4, "cardSetId": 1637, "rarityId": 1, "artistName": "Peter Stapleton", "health": 2, "attack": 2, "manaCost": 2, "name": "Grimestreet Outfitter", "text": "<b>Battlecry:</b> Give all minions in your hand +1/+1.", "image": "https://d15f34w2p8l1cc.cloudfront.net/hearthstone/919d3ee4ac2281a96a8ca8427a2af2454a241c7ffb3a830b50ed8fe2431305a6.png", "imageGold": "", "flavorText": "If you bargain hard, he'll throw in the hat.", "cropImage": "https://d15f34w2p8l1cc.cloudfront.net/hearthstone/5a103112c139226d946f28d7fdffe0fa4fb993c9e93ccbc1a0e10a5e8b33a7c3.png", "keywordIds": [8], "copyOfCardId": 40567, "isZilliaxFunctionalModule": false, "isZilliaxCosmeticModule": false}, {"id": 95630, "collectible": 1, "slug": "95630-grimtotem-buzzkill", "classId": 12, "multiClassIds": [], "cardTypeId": 4, "cardSetId": 1809, "rarityId": 4, "artistName": "Mike Sass", "health": 4, "attack": 5, "manaCost": 4, "name": "Grimtotem Buzzkill", "text": "<b>Battlecry:</b> Discard a weapon to draw 3 cards.", "image": "https://d15f34w2p8l1cc.cloudfront.net/hearthstone/c9cb8866671642cfc7196f8d0d07219e3e854e808fb9d37a2bfa021bce4207a0.png", "imageGold": "", "flavorText": "I'd be mad too if you called me a 'buzzkill'.", "cropImage": "https://d15f34w2p8l1cc.cloudfront.net/hearthstone/0250b49dba06f4517faaf4f6169046d681726f3200a8a5437b14d7de8d2cf086.png", "keywordIds": [8], "isZilliaxFunctionalModule": false, "isZilliaxCosmeticModule": false}, {"id": 69643, "collectible": 1, "slug": "69643-grommash-hellscream", "classId": 10, "multiClassIds": [], "cardTypeId": 4, "cardSetId": 1637, "rarityId": 5, "artistName": "Glenn Rane", "health": 9, "attack": 4, "manaCost": 8, "name": "Grommash Hellscream", "text": "<b>Charge</b> Has +6 Attack while damaged.", "image": "https://d15f34w2p8l1cc.cloudfront.net/hearthstone/d37389900dd48b4354c18fd58dd8e14080ee121c52ee6a1c4094672879a90040.png", "imageGold": "", "flavorText": "Grommash drank the tainted blood of Mannoroth, dooming the orcs to green skin and red eyes! Maybe not his best decision.", "cropImage": "https://d15f34w2p8l1cc.cloudfront.net/hearthstone/097beabe6b708283c29683939a4f4b0193b1194039abd8e69428926a3b7688d0.png", "keywordIds": [4], "copyOfCardId": 338, "isZilliaxFunctionalModule": false, "isZilliaxCosmeticModule": false}, {"id": 94249, "collectible": 1, "slug": "94249-groovy-cat", "classId": 2, "multiClassIds": [], "minionTypeId": 20, "cardTypeId": 4, "cardSetId": 1809, "rarityId": 3, "artistName": "Eva Widermann", "health": 1, "attack": 2, "manaCost": 2, "name": "Groovy Cat", "text": "<b>Battlecry and Deathrattle:</b> Your Hero Power gives your hero 1 more Attack this game.", "image": "https://d15f34w2p8l1cc.cloudfront.net/hearthstone/81e35c290ee1d8f9bd90dda2702b59ba04fc12cb59745831e30b97e6cecd6a2c.png", "imageGold": "", "flavorText": "\"Like, what if we're all just cards living in this box called Hearthstone, man?\"", "cropImage": "https://d15f34w2p8l1cc.cloudfront.net/hearthstone/38b01cc88cf74944a690028598e483564d6b71c8d9192e6f01426cefd51c27f5.png", "keywordIds": [8, 12], "isZilliaxFunctionalModule": false, "isZilliaxCosmeticModule": false}, {"id": 87639, "collectible": 1, "slug": "87639-guitar-soloist", "classId": 14, "multiClassIds": [], "cardTypeId": 4, "cardSetId": 1809, "rarityId": 1, "artistName": "Nicola Saviori", "health": 3, "attack": 4, "manaCost": 5, "name": "Guitar Soloist", "text": "<b>Battlecry:</b> If you control no other minions, draw a spell, a minion, and a weapon.", "image": "https://d15f34w2p8l1cc.cloudfront.net/hearthstone/753f3e598cdcb94cd4712a640190075f21e41389ac59e4aa32e48d4ead98280d.png", "imageGold": "", "flavorText": "She is the hero of the guitar. The guitar hero. Trademark.", "cropImage": "https://d15f34w2p8l1cc.cloudfront.net/hearthstone/9ce44e8c0b43d9809002e4c25ea0ffc37300c79bfe5316b47cd1207449d5555e.png", "keywordIds": [8], "isZilliaxFunctionalModule": false, "isZilliaxCosmeticModule": false}, {"id": 103664, "collectible": 1, "slug": "103664-guldans-gift", "classId": 9, "multiClassIds": [], "cardTypeId": 5, "cardSetId": 1941, "rarityId": 3, "artistName": "Alex Stone", "manaCost": 1, "name": "Gul'dan's Gift", "text": "<b>Discover</b> a temporary Mortal Coil, Siphon Soul, or Twisting Nether.", "image": "https://d15f34w2p8l1cc.cloudfront.net/hearthstone/6b12aa92be91ee10988f38ab49307c2f2d84af46908d4c029bc37370ba49179d.png", "imageGold": "", "flavorText": "\"This won't be like last time...\" -Gul'dan", "cropImage": "https://d15f34w2p8l1cc.cloudfront.net/hearthstone/230ac7b86c4417f75e45dcba573385923465e8e0566d289f97496126a261c861.png", "childIds": [69553, 69634, 69635], "keywordIds": [21], "isZilliaxFunctionalModule": false, "isZilliaxCosmeticModule": false}, {"id": 98652, "collectible": 1, "slug": "98652-gunslinger-kurtrus", "classId": 14, "multiClassIds": [], "cardTypeId": 4, "cardSetId": 1892, "rarityId": 5, "artistName": "Alex Horley Orlandelli", "health": 6, "attack": 4, "manaCost": 5, "name": "Gunslinger Kurtrus", "text": "<b>Battlecry:</b> If your deck started with no duplicates, fire six 2 damage shots at minions in the enemy's hand.", "image": "https://d15f34w2p8l1cc.cloudfront.net/hearthstone/68c81fcea448490b522169b1f0d54e7bccdfb2b40ad1b4421f917d69bbfbf72a.png", "imageGold": "", "flavorText": "\"I have given up (a single copy of) EVERYTHING! What have YOU sacrificed?\"", "cropImage": "https://d15f34w2p8l1cc.cloudfront.net/hearthstone/b567a98305465daf3c15063bfceff4d6d930fc76caf396f660918ba597749929.png", "keywordIds": [8], "isZilliaxFunctionalModule": false, "isZilliaxCosmeticModule": false}, {"id": 103124, "collectible": 1, "slug": "103124-hagatha-the-fabled", "classId": 8, "multiClassIds": [], "cardTypeId": 4, "cardSetId": 1897, "rarityId": 5, "artistName": "Jakub Kasper", "health": 3, "attack": 4, "manaCost": 4, "name": "Hagatha the Fabled", "text": "<b>Battlecry:</b> Draw 2 spells that cost (5) or more. Transform them into Slimes that cast the spells.", "image": "https://d15f34w2p8l1cc.cloudfront.net/hearthstone/cb6d1a1a9146cef584df6f4d042642ea893a16c65ed55b369fa8b8a01abf2a91.png", "imageGold": "", "flavorText": "Soup's on!", "cropImage": "https://d15f34w2p8l1cc.cloudfront.net/hearthstone/1d8792a3c102ab77b0ba9af1d24785fcf3d0d0f9bdf2ccfb1ddf4194437dba74.png", "childIds": [103125], "keywordIds": [8], "isZilliaxFunctionalModule": false, "isZilliaxCosmeticModule": false}, {"id": 96999, "collectible": 1, "slug": "96999-halveria-darkraven", "classId": 14, "multiClassIds": [], "cardTypeId": 4, "cardSetId": 1809, "rarityId": 5, "artistName": "Rafael Zanchetin", "health": 3, "attack": 4, "manaCost": 4, "name": "Halveria Darkraven", "text": "<b>Rush</b> After a friendly <b>Rush</b> minion attacks, give your minions +1 Attack.", "image": "https://d15f34w2p8l1cc.cloudfront.net/hearthstone/1a2f13f6b52f1323ea48c8e9804052c4fe22eec54adb878181ebc00f87125620.png", "imageGold": "", "flavorText": "You know someone's cool when their name sounds like a font.", "cropImage": "https://d15f34w2p8l1cc.cloudfront.net/hearthstone/05c14007a4d55d114c0878c138cc22080a5072f72dc5117bc3b509f4b82708b9.png", "keywordIds": [53], "isZilliaxFunctionalModule": false, "isZilliaxCosmeticModule": false}, {"id": 102790, "collectible": 1, "slug": "102790-hammer-of-wrath", "classId": 5, "multiClassIds": [], "spellSchoolId": 5, "cardTypeId": 5, "cardSetId": 1637, "rarityId": 1, "artistName": "Efrem Palacios", "manaCost": 3, "name": "Hammer of Wrath", "text": "Deal 3 damage. Draw a card.", "image": "https://d15f34w2p8l1cc.cloudfront.net/hearthstone/ec845bb99e62ac633f7c8b99497cfdd0a10be4dadb863e5d573503012dae20e9.png", "imageGold": "", "flavorText": "A good paladin has many tools. Hammer of Wrath, Pliers of Vengeance, Hacksaw of Justice, etc.", "cropImage": "https://d15f34w2p8l1cc.cloudfront.net/hearthstone/ad0a98eee4b29185eb0b6d45bd40409cb517b93ad696a8cb92b255ace0e48e4c.png", "copyOfCardId": 250, "isZilliaxFunctionalModule": false, "isZilliaxCosmeticModule": false}, {"id": 111370, "collectible": 1, "slug": "111370-hammer-of-the-naaru", "classId": 5, "multiClassIds": [], "cardTypeId": 7, "cardSetId": 1637, "rarityId": 4, "artistName": "SARIYA", "attack": 3, "manaCost": 6, "durability": 3, "name": "Hammer of the Naaru", "text": "<b>Battlecry:</b> Summon a 6/6 Holy Elemental with <b>Taunt</b>.", "image": "https://d15f34w2p8l1cc.cloudfront.net/hearthstone/9f83fc0d73fe8c7b86ab93a5fd0ee69665fff20790d7a7b8a4d20093cd6c3f83.png", "imageGold": "", "flavorText": "The naaru wasn't using it. It doesn't have arms.", "cropImage": "https://d15f34w2p8l1cc.cloudfront.net/hearthstone/68b4ddb4696a565438981dd30ef02022a325c4862f480e770fe42bf11ca503a8.png", "childIds": [62190], "keywordIds": [1, 8], "copyOfCardId": 61189, "isZilliaxFunctionalModule": false, "isZilliaxCosmeticModule": false}, {"id": 102197, "collectible": 1, "slug": "102197-hand-of-adal", "classId": 5, "multiClassIds": [], "spellSchoolId": 5, "cardTypeId": 5, "cardSetId": 1637, "rarityId": 1, "artistName": "Anton Zemskov", "manaCost": 2, "name": "Hand of A'dal", "text": "Give a minion +2/+1. Draw a card.", "image": "https://d15f34w2p8l1cc.cloudfront.net/hearthstone/f28cd009aa8c2e01a27fdee7076dc2afd0e961ae5fb3d9ca42fa095740e7534f.png", "imageGold": "", "flavorText": "When it meets the Hand of Gul'dan, they're SHAKING.", "cropImage": "https://d15f34w2p8l1cc.cloudfront.net/hearthstone/42b62967619f3b4ee9269e12596d6383ab324447ea52ef60a2d2e32abadbcb92.png", "copyOfCardId": 57546, "isZilliaxFunctionalModule": false, "isZilliaxCosmeticModule": false}, {"id": 81972, "collectible": 1, "slug": "81972-harbinger-of-winter", "classId": 1, "multiClassIds": [], "minionTypeId": 11, "cardTypeId": 4, "cardSetId": 1637, "rarityId": 1, "artistName": "Angelina Chernyak", "health": 2, "attack": 3, "manaCost": 2, "name": "Harbinger of Winter", "text": "<b>Deathrattle:</b> Draw a Frost spell.", "image": "https://d15f34w2p8l1cc.cloudfront.net/hearthstone/8f6a6ae5cfc1e0f2bf6601783e0081c0b57e65ac768131788232d9f3002d049c.png", "imageGold": "", "flavorText": "Winter: it be comin'.", "cropImage": "https://d15f34w2p8l1cc.cloudfront.net/hearthstone/b949478e7f46d075fa506077cdb9b2f1274cf250e7b774434634e31c96a99316.png", "keywordIds": [12], "isZilliaxFunctionalModule": false, "isZilliaxCosmeticModule": false, "runeCost": {"blood": 0, "frost": 1, "unholy": 0}}, {"id": 97528, "collectible": 1, "slug": "97528-hardcore-cultist", "classId": 1, "multiClassIds": [], "minionTypeId": 11, "cardTypeId": 4, "cardSetId": 1809, "rarityId": 1, "artistName": "Mooncolony ", "health": 1, "attack": 2, "manaCost": 3, "name": "Hardcore Cultist", "text": "<b>Battlecry:</b> Deal 2 damage. <b>Finale:</b> To all enemies.", "image": "https://d15f34w2p8l1cc.cloudfront.net/hearthstone/841c2edea68407f20e002426f93c1e5f1baaad3fb91e74ff834e519758dc72f8.png", "imageGold": "", "flavorText": "Thumb in = devil horns. Thumb out = I love you. A VERY important distinction when you're at a metal concert.", "cropImage": "https://d15f34w2p8l1cc.cloudfront.net/hearthstone/54cf0f2dedc82e59ac0af831f9170ae24046ef86d8ad84f43075c2f6337793cd.png", "keywordIds": [8, 255], "isZilliaxFunctionalModule": false, "isZilliaxCosmeticModule": false, "runeCost": {"blood": 0, "frost": 1, "unholy": 0}}, {"id": 88580, "collectible": 1, "slug": "88580-harmonic-disco", "classId": 5, "multiClassIds": [], "spellSchoolId": 5, "cardTypeId": 5, "cardSetId": 1809, "rarityId": 3, "artistName": "Vlad Botos", "manaCost": 5, "name": "Harmonic Disco", "text": "<b>Discover</b> a 5-Cost minion. Summon it with +1/+1. <i>(Swaps each turn.)</i>", "image": "https://d15f34w2p8l1cc.cloudfront.net/hearthstone/bd55e3c85c05ac5424ddd6f20353ae287b23afb30c19cb1ce70bd0f8a65ec823.png", "imageGold": "", "flavorText": "\"Worry not, festival patrons! A disco is hardly any means for panic!\"", "cropImage": "https://d15f34w2p8l1cc.cloudfront.net/hearthstone/b25529125db0cb326734e323f26b7df91dd2ae871d9905d64166ad5ba3d79a7b.png", "childIds": [88555], "keywordIds": [21], "isZilliaxFunctionalModule": false, "isZilliaxCosmeticModule": false}, {"id": 88403, "collectible": 1, "slug": "88403-harmonic-hip-hop", "classId": 7, "multiClassIds": [], "spellSchoolId": 6, "cardTypeId": 5, "cardSetId": 1809, "rarityId": 3, "artistName": "Patrik Bjorkstrom", "manaCost": 2, "name": "Harmonic Hip Hop", "text": "Deal 1 damage. Give your weapon +3 Attack. <i>(Swaps each turn.)</i>", "image": "https://d15f34w2p8l1cc.cloudfront.net/hearthstone/c7cab855b810cc163d0d31b0c8234db7fb353030e8b5380f0748d186f7c5f55a.png", "imageGold": "", "flavorText": "I can name four things that rhyme with 'orange': Four inch, Door hinge, Syringe, and uh\u2026 Shmorange.", "cropImage": "https://d15f34w2p8l1cc.cloudfront.net/hearthstone/ccc2a7fe2774c4872a5c1bce39ed782103c2f20e49399b5a053860dcfd270a74.png", "childIds": [90921], "isZilliaxFunctionalModule": false, "isZilliaxCosmeticModule": false}, {"id": 91412, "collectible": 1, "slug": "91412-harmonic-metal", "classId": 1, "multiClassIds": [], "cardTypeId": 5, "cardSetId": 1809, "rarityId": 1, "artistName": "Konstantin Porubov", "manaCost": 3, "name": "Harmonic Metal", "text": "Give 4 random minions in your hand +2/+2. <i>(Swaps each turn.)</i>", "image": "https://d15f34w2p8l1cc.cloudfront.net/hearthstone/65671349575a6880638b52b04d3df75f58455b528bfd7f31123f86944b5bacc6.png", "imageGold": "", "flavorText": "I have bashed together plenty of pieces of metal in my day and not ONCE has it sounded harmonic.", "cropImage": "https://d15f34w2p8l1cc.cloudfront.net/hearthstone/345e12d52d1e96ecff83022c6ab344449e32ba19b62e4b4052da5dd195c7040a.png", "childIds": [91415], "isZilliaxFunctionalModule": false, "isZilliaxCosmeticModule": false, "runeCost": {"blood": 1, "frost": 0, "unholy": 0}}, {"id": 94210, "collectible": 1, "slug": "94210-harmonic-mood", "classId": 2, "multiClassIds": [], "cardTypeId": 5, "cardSetId": 1809, "rarityId": 1, "artistName": "Ivan Fomin", "manaCost": 2, "name": "Harmonic Mood", "text": "Give your hero +2 Attack this turn. Gain 4 Armor. <i>(Swaps each turn.)</i>", "image": "https://d15f34w2p8l1cc.cloudfront.net/hearthstone/13550d88ca568ebbfd81372d2b31ddd7b4b21c5b9caddbe0da014105e2e38ec4.png", "imageGold": "", "flavorText": "ROYGBive your hero +2 Attack this turn.", "cropImage": "https://d15f34w2p8l1cc.cloudfront.net/hearthstone/038f6fb41935686db8328397199680881338c428ef76f360e19ca6e8cacefa55.png", "childIds": [94211], "isZilliaxFunctionalModule": false, "isZilliaxCosmeticModule": false}, {"id": 90683, "collectible": 1, "slug": "90683-harmonic-pop", "classId": 6, "multiClassIds": [], "spellSchoolId": 5, "cardTypeId": 5, "cardSetId": 1809, "rarityId": 3, "artistName": "Vika Yarova", "manaCost": 6, "name": "Harmonic Pop", "text": "Deal 3 damage to all minions. Summon a 6/6 Popstar. <i>(Swaps each turn.)</i>", "image": "https://d15f34w2p8l1cc.cloudfront.net/hearthstone/3c9e62fbfa40b05a49365299489ffd073e320e07b873e1ad433e243459b6b332.png", "imageGold": "", "flavorText": "Here with supporting vocals: Snap and Crackle!", "cropImage": "https://d15f34w2p8l1cc.cloudfront.net/hearthstone/6d89760a5e7778d5c62587dc7fc9346bcc320d38ac8b78380759f922dc5059a3.png", "childIds": [97461, 97459], "isZilliaxFunctionalModule": false, "isZilliaxCosmeticModule": false}, {"id": 87642, "collectible": 1, "slug": "87642-harmonica-soloist", "classId": 3, "multiClassIds": [], "cardTypeId": 4, "cardSetId": 1809, "rarityId": 4, "artistName": "Mooncolony ", "health": 2, "attack": 4, "manaCost": 3, "name": "Harmonica Soloist", "text": "<b>Battlecry:</b> If you control no other minions, <b>Discover</b> and cast a <b>Secret</b>.", "image": "https://d15f34w2p8l1cc.cloudfront.net/hearthstone/9d69c889513467616d2ecba582f92e282e7375fdd0b995c747ac9b5571aac4ca.png", "imageGold": "", "flavorText": "A magician never reveals their Secrets. A musician on the other hand...", "cropImage": "https://d15f34w2p8l1cc.cloudfront.net/hearthstone/848163d0b9d50fa897520ce743bf21a8c058453c0a2d104e4c711301e90ff009.png", "keywordIds": [5, 8, 21], "isZilliaxFunctionalModule": false, "isZilliaxCosmeticModule": false}, {"id": 100616, "collectible": 1, "slug": "100616-harrowing-ox", "classId": 1, "multiClassIds": [], "minionTypeId": 11, "multiTypeIds": [20], "cardTypeId": 4, "cardSetId": 1892, "rarityId": 4, "artistName": "Mauricio Herrera", "health": 7, "attack": 7, "manaCost": 7, "name": "Harrowing Ox", "text": "<b>Taunt</b> <b>Battlecry:</b> If you've <b>Excavated</b> twice, your next card this turn costs (7) less.", "image": "https://d15f34w2p8l1cc.cloudfront.net/hearthstone/d3fcb4a80df6531a6fd279f066ab34471fc8c2b3a747c03aad5c448cb76ebdc9.png", "imageGold": "", "flavorText": "Dead or alive, you're pulling that plow.", "cropImage": "https://d15f34w2p8l1cc.cloudfront.net/hearthstone/c73454c8eda5008b6c467271c72da1dbed6fa4834a89985309099fde3648751f.png", "keywordIds": [1, 8, 298], "isZilliaxFunctionalModule": false, "isZilliaxCosmeticModule": false, "runeCost": {"blood": 0, "frost": 1, "unholy": 0}}, {"id": 103654, "collectible": 1, "slug": "103654-harth-stonebrew", "classId": 12, "multiClassIds": [], "cardTypeId": 4, "cardSetId": 1941, "rarityId": 5, "artistName": "Arthur Gimaldinov", "health": 5, "attack": 5, "manaCost": 6, "name": "Harth Stonebrew", "text": "<b>Battlecry:</b> Replace your hand with an iconic one from Hearthstone's past. <i>(Once per game)</i>", "image": "https://d15f34w2p8l1cc.cloudfront.net/hearthstone/4529dcdf70c0f9dd5a52ed2619735c3465a5cecd4e32b1036e588e28a6fdbb94.png", "imageGold": "", "flavorText": "\"Grab a slice by the hearth and enjoy the festivities. This celebration is for all of us!\" -Harth", "cropImage": "https://d15f34w2p8l1cc.cloudfront.net/hearthstone/e2c8cd22fb08395f09ade9ceda90d29c0c09bb414a91bb0210ac2cdbc2857908.png", "keywordIds": [8], "isZilliaxFunctionalModule": false, "isZilliaxCosmeticModule": false}, {"id": 90956, "collectible": 1, "slug": "90956-heartbreaker-hedanis", "classId": 6, "multiClassIds": [], "cardTypeId": 4, "cardSetId": 1809, "rarityId": 5, "artistName": "Dez Bencosme", "health": 8, "attack": 4, "manaCost": 4, "name": "Heartbreaker Hedanis", "text": "<b>Battlecry:</b> Deal 4 damage to this minion. <b>Overheal:</b> Deal 5 damage to a random enemy.", "image": "https://d15f34w2p8l1cc.cloudfront.net/hearthstone/d54d7416f493e47defc21cc733e1ea8e30403817cf1f8f50383a03fab3d6db8d.png", "imageGold": "", "flavorText": "Hedanis has won over the hearts and minds of millions of fans all over Azeroth! Shadow magic had nothing to do with it - not that you asked or anything.", "cropImage": "https://d15f34w2p8l1cc.cloudfront.net/hearthstone/82bc19d1bb0e3f72de31f03f63d7bb289ca80814b1ad70697a830f2bd2109452.png", "keywordIds": [8, 256], "isZilliaxFunctionalModule": false, "isZilliaxCosmeticModule": false}, {"id": 91079, "collectible": 1, "slug": "91079-heartthrob", "classId": 6, "multiClassIds": [], "minionTypeId": 11, "cardTypeId": 4, "cardSetId": 1809, "rarityId": 4, "artistName": "Valeria Styajkina", "health": 5, "attack": 2, "manaCost": 3, "name": "Heartthrob", "text": "<b>Overheal:</b> Summon a random minion with Cost equal to the amount <b>Overhealed</b>.", "image": "https://d15f34w2p8l1cc.cloudfront.net/hearthstone/63e28c77bf301048de3f743c11d257ab087750dd5b1009d9ec4beaac15250372.png", "imageGold": "", "flavorText": "Oh no, Harth! Look out! He's here to rob you!", "cropImage": "https://d15f34w2p8l1cc.cloudfront.net/hearthstone/29d42b28eda4fdf971826c6b7ae1e3660cf4ebd8ef33cf2de305f12b7bd25888.png", "keywordIds": [256], "isZilliaxFunctionalModule": false, "isZilliaxCosmeticModule": false}, {"id": 101462, "collectible": 1, "slug": "101462-heat-wave", "classId": 4, "multiClassIds": [], "spellSchoolId": 2, "cardTypeId": 5, "cardSetId": 1892, "rarityId": 3, "artistName": "Grafit ", "manaCost": 2, "name": "Heat Wave", "text": "Deal 2 damage to an enemy minion and its neighbors. <b>Quickdraw:</b> To all enemies instead.", "image": "https://d15f34w2p8l1cc.cloudfront.net/hearthstone/e29569b7c8666b03db6ec7e03b7e96ce58394ad489d3c6de2508b9d9b5003436.png", "imageGold": "", "flavorText": "This is the hottest summer of your life <i>so far</i>.", "cropImage": "https://d15f34w2p8l1cc.cloudfront.net/hearthstone/039ec63e527b3cb37b690f41673711b0660a23825650345534011497e244660a.png", "keywordIds": [297], "isZilliaxFunctionalModule": false, "isZilliaxCosmeticModule": false}, {"id": 97333, "collectible": 1, "slug": "97333-heavy-plate", "classId": 10, "multiClassIds": [], "cardTypeId": 5, "cardSetId": 1637, "rarityId": 1, "artistName": "Matt Dixon", "manaCost": 3, "name": "Heavy Plate", "text": "<b>Tradeable</b> Gain 8 Armor.", "image": "https://d15f34w2p8l1cc.cloudfront.net/hearthstone/e4c6ccb577f3fc470ff43da1e06cefcdd3db461a62b970d3b4b89091bd1ccec4.png", "imageGold": "", "flavorText": "\"You asked for unbendable, unwavering armor\u2013I don't see why you're upset.\"", "cropImage": "https://d15f34w2p8l1cc.cloudfront.net/hearthstone/c247f22890ddd5b1edbdc1544d7542be5478d79ddf40d87af31a7bbdd7756e55.png", "keywordIds": [97], "copyOfCardId": 65656, "isZilliaxFunctionalModule": false, "isZilliaxCosmeticModule": false}, {"id": 69519, "collectible": 1, "slug": "69519-hellfire", "classId": 9, "multiClassIds": [], "spellSchoolId": 2, "cardTypeId": 5, "cardSetId": 1637, "rarityId": 1, "artistName": "Chippy", "manaCost": 3, "name": "Hellfire", "text": "Deal 3 damage to ALL characters.", "image": "https://d15f34w2p8l1cc.cloudfront.net/hearthstone/5d75e7607eee0da08248662318f66e0d413a56f15a503640fd296c87c91cae95.png", "imageGold": "", "flavorText": "It's spells like these that make it hard for Warlocks to get decent help.", "cropImage": "https://d15f34w2p8l1cc.cloudfront.net/hearthstone/d5f171717267d086235dd34f50ba0d1d9935c312c01339ea2ea8ffa319ad3edc.png", "copyOfCardId": 950, "isZilliaxFunctionalModule": false, "isZilliaxCosmeticModule": false}, {"id": 105511, "collectible": 1, "slug": "105511-helm-of-humiliation", "classId": 1, "multiClassIds": [], "spellSchoolId": 6, "cardTypeId": 5, "cardSetId": 1897, "rarityId": 3, "artistName": "Anton Zemskov", "manaCost": 4, "name": "Helm of Humiliation", "text": "Give a minion -5/-5. Give a minion in your hand +5/+5.", "image": "https://d15f34w2p8l1cc.cloudfront.net/hearthstone/be4a121be5d1bd5d04e4d61f1fdebcb2e452c5d1b28d307fd571643ee0b78630.png", "imageGold": "", "flavorText": "<whispers> \"...and your father was a Murloc too.\"", "cropImage": "https://d15f34w2p8l1cc.cloudfront.net/hearthstone/9ba61f853b812abe8d75c0547b396db55561f072e7c76b3eb67e97ff0b76eb67.png", "isZilliaxFunctionalModule": false, "isZilliaxCosmeticModule": false, "runeCost": {"blood": 2, "frost": 0, "unholy": 0}}, {"id": 97683, "collectible": 1, "slug": "97683-helya", "classId": 1, "multiClassIds": [], "cardTypeId": 4, "cardSetId": 1858, "rarityId": 5, "artistName": "Anton Zemskov", "health": 4, "attack": 4, "manaCost": 4, "name": "Helya", "text": "<b>Battlecry:</b> Shuffle all three Plagues into your opponent's deck. Plagues they draw this game are unending.", "image": "https://d15f34w2p8l1cc.cloudfront.net/hearthstone/ba9a5814f534e370ce8a855a8fb3a1c946da2fe1608f439936b6f65c6b07ed78.png", "imageGold": "", "flavorText": "Named after the first thing Odyn said after landing a sick kickflip.", "cropImage": "https://d15f34w2p8l1cc.cloudfront.net/hearthstone/cdbf93663cbd1e149f23def5d1c2d42d0baa90728887ed543be89495c46f4854.png", "childIds": [101924, 101928, 101927, 78608], "keywordIds": [8], "isZilliaxFunctionalModule": false, "isZilliaxCosmeticModule": false, "runeCost": {"blood": 0, "frost": 0, "unholy": 1}}, {"id": 111320, "collectible": 1, "slug": "111320-hematurge", "classId": 1, "multiClassIds": [], "cardTypeId": 4, "cardSetId": 1637, "rarityId": 3, "artistName": "Dez Bencosme", "health": 3, "attack": 2, "manaCost": 2, "name": "Hematurge", "text": "<b>Battlecry:</b> Spend a <b>Corpse</b> to <b>Discover</b> a Blood Rune card.", "image": "https://d15f34w2p8l1cc.cloudfront.net/hearthstone/7c45a79df17e6dde4e2591dc4ea55119534124e1f24298abbebd0dfb9e570a96.png", "imageGold": "", "flavorText": "She's here to PUMP! YOU UP!", "cropImage": "https://d15f34w2p8l1cc.cloudfront.net/hearthstone/8b7130c4f7a84d789815893723d77b55911b17f61e0ab62e4fddf10316df59af.png", "keywordIds": [8, 21, 247], "copyOfCardId": 78356, "isZilliaxFunctionalModule": false, "isZilliaxCosmeticModule": false, "runeCost": {"blood": 1, "frost": 0, "unholy": 0}}, {"id": 103156, "collectible": 1, "slug": "103156-hemet-foam-marksman", "classId": 3, "multiClassIds": [], "cardTypeId": 4, "cardSetId": 1897, "rarityId": 5, "artistName": "Juan Calle", "health": 6, "attack": 3, "manaCost": 5, "name": "Hemet, Foam Marksman", "text": "After a friendly Beast dies, get a random <b>Legendary</b> Beast from the past. It costs (2) less.", "image": "https://d15f34w2p8l1cc.cloudfront.net/hearthstone/52255b206732a164bf02710ac6584691a8ae59b73719a6bc6f01670e324e28a5.png", "imageGold": "", "flavorText": "So THIS is who's been lowering the power level of all those Hearthstone cards in a foamly fashion.", "cropImage": "https://d15f34w2p8l1cc.cloudfront.net/hearthstone/00e61c83d1d335464c71046ef867a525d92a2ca69c66e03ae311338a43c82ba0.png", "isZilliaxFunctionalModule": false, "isZilliaxCosmeticModule": false}, {"id": 86540, "collectible": 1, "slug": "86540-hench-clan-burglar", "classId": 7, "multiClassIds": [], "minionTypeId": 23, "cardTypeId": 4, "cardSetId": 1637, "rarityId": 1, "artistName": "Anton Zemskov", "health": 4, "attack": 4, "manaCost": 4, "name": "Hench-Clan Burglar", "text": "<b>Battlecry:</b> <b>Discover</b> a spell from another class.", "image": "https://d15f34w2p8l1cc.cloudfront.net/hearthstone/d4c5a7fe4bf896531b57afb17c8b1558df4db41d76eb6be723a88e23f8087b9d.png", "imageGold": "", "flavorText": "She\u2019s more of a rat burglar.", "cropImage": "https://d15f34w2p8l1cc.cloudfront.net/hearthstone/6e6cb624a9af867993a4e79f96e766681db38f0d153aef8d375019e235117a77.png", "keywordIds": [8, 21], "copyOfCardId": 52112, "isZilliaxFunctionalModule": false, "isZilliaxCosmeticModule": false}, {"id": 97343, "collectible": 1, "slug": "97343-hench-clan-thug", "classId": 12, "multiClassIds": [], "minionTypeId": 43, "cardTypeId": 4, "cardSetId": 1637, "rarityId": 1, "artistName": "A. J. Nazzaro", "health": 3, "attack": 3, "manaCost": 3, "name": "Hench-Clan Thug", "text": "After your hero attacks, give this minion +1/+1.", "image": "https://d15f34w2p8l1cc.cloudfront.net/hearthstone/00b1ea2c86f704e87644779665563c44fc1111c6b3459d620d43ecf5bcbb4bd4.png", "imageGold": "", "flavorText": "Hard time making ends meet? Hate the League of Explorers? Get a job henching!", "cropImage": "https://d15f34w2p8l1cc.cloudfront.net/hearthstone/1a966d11b5c68ca3766a2cb31b649f86c20230880bb272c26a39abad87cd1dd6.png", "copyOfCardId": 47014, "isZilliaxFunctionalModule": false, "isZilliaxCosmeticModule": false}, {"id": 69551, "collectible": 1, "slug": "69551-hex", "classId": 8, "multiClassIds": [], "spellSchoolId": 4, "cardTypeId": 5, "cardSetId": 1637, "rarityId": 1, "artistName": "Steve Hui", "manaCost": 3, "name": "Hex", "text": "Transform a minion into a 0/1 Frog with <b>Taunt</b>.", "image": "https://d15f34w2p8l1cc.cloudfront.net/hearthstone/9786b58975f3e0c767f9ffcd68c5af6b73fc762591c9dbdd8afb6ce596b5a059.png", "imageGold": "", "flavorText": "If you Hex a Murloc... it really isn't much of a change, is it?", "cropImage": "https://d15f34w2p8l1cc.cloudfront.net/hearthstone/d3c1ec46dfffdf70c140b24c0e62d59b61a7b706eb8dc8b7d26ed8b8594cd21c.png", "childIds": [548], "keywordIds": [1], "copyOfCardId": 766, "isZilliaxFunctionalModule": false, "isZilliaxCosmeticModule": false}, {"id": 100284, "collectible": 1, "slug": "100284-hi-ho-silverwing", "classId": 5, "multiClassIds": [], "minionTypeId": 24, "cardTypeId": 4, "cardSetId": 1892, "rarityId": 3, "artistName": "A. Gimaldinov & J. Nelson", "health": 1, "attack": 2, "manaCost": 2, "name": "Hi Ho Silverwing", "text": "<b>Divine Shield</b> <b>Deathrattle:</b> Draw a Holy spell.", "image": "https://d15f34w2p8l1cc.cloudfront.net/hearthstone/edae9c3eb3651b75d94eda5510a2587f0752fbae1a19317fd0b7653011ee8459.png", "imageGold": "", "flavorText": "I swear this minion had 3000 Attack at one point!", "cropImage": "https://d15f34w2p8l1cc.cloudfront.net/hearthstone/8cab0662b176a6b646257939920901662542b3bc562f99870878bc9b618ea45d.png", "keywordIds": [3, 12], "isZilliaxFunctionalModule": false, "isZilliaxCosmeticModule": false}, {"id": 102422, "collectible": 1, "slug": "102422-hidden-gem", "classId": 6, "multiClassIds": [6, 7], "minionTypeId": 18, "cardTypeId": 4, "cardSetId": 1892, "rarityId": 1, "artistName": "Patrik Bjorkstrom", "health": 2, "attack": 2, "manaCost": 2, "name": "Hidden Gem", "text": "<b>Stealth</b> At the end of your turn, restore 2 Health to all friendly characters.", "image": "https://d15f34w2p8l1cc.cloudfront.net/hearthstone/4c9cf6592bc7ab2080db6f90d9e4f3d85f44bb0987fee893408abd41dd3764aa.png", "imageGold": "", "flavorText": "This will be a staple in Unicorn Priest.", "cropImage": "https://d15f34w2p8l1cc.cloudfront.net/hearthstone/0c3952dc872ac5ca8ac06e2fbbfdae6fe8dcca0a7018b13480a042f080392f18.png", "keywordIds": [6], "isZilliaxFunctionalModule": false, "isZilliaxCosmeticModule": false}, {"id": 96618, "collectible": 1, "slug": "96618-hidden-meaning", "classId": 3, "multiClassIds": [], "cardTypeId": 5, "cardSetId": 1809, "rarityId": 3, "artistName": "Kevin Sidharta", "manaCost": 2, "name": "Hidden Meaning", "text": "<b>Secret:</b> When your opponent ends their turn with no Mana, summon a random 3-Cost minion.", "image": "https://d15f34w2p8l1cc.cloudfront.net/hearthstone/c2ed3bd159d67974e01cc4483a52a97d2ebecb896cc1bcfdff0612edbbafbeb1.png", "imageGold": "", "flavorText": "I'm telling you, if you play the song backwards at triple speed I SWEAR Mukla sings about the Burning Legion.", "cropImage": "https://d15f34w2p8l1cc.cloudfront.net/hearthstone/1d0d218161bdbaab2f39958f1c82472c0aa76d6e95404872277f9bea29fe9fb8.png", "keywordIds": [5], "isZilliaxFunctionalModule": false, "isZilliaxCosmeticModule": false}, {"id": 102449, "collectible": 1, "slug": "102449-hidden-objects", "classId": 4, "multiClassIds": [], "cardTypeId": 5, "cardSetId": 1897, "rarityId": 1, "artistName": "BOSi Studio", "manaCost": 2, "name": "Hidden Objects", "text": "<b>Discover</b> a <b>Secret</b>. Set its Cost to (1).", "image": "https://d15f34w2p8l1cc.cloudfront.net/hearthstone/62e1338374277dfef0a5977d9725287d0c73391e4ee390609ce67b1b03bfd0b7.png", "imageGold": "", "flavorText": "There are 99 gnomes in this picture. Can YOU find them all?", "cropImage": "https://d15f34w2p8l1cc.cloudfront.net/hearthstone/317bf6574b68c52a308fbff5cd0208b686c487aecd78974fecb3d467bf1bffe8.png", "keywordIds": [5, 21], "isZilliaxFunctionalModule": false, "isZilliaxCosmeticModule": false}, {"id": 102171, "collectible": 1, "slug": "102171-high-noon-duelist", "classId": 12, "multiClassIds": [], "cardTypeId": 4, "cardSetId": 1892, "rarityId": 1, "artistName": "James Ryman", "health": 3, "attack": 4, "manaCost": 3, "name": "High Noon Duelist", "text": "<b>Deathrattle:</b> Both players DRAW! Destroy the card that costs less.", "image": "https://d15f34w2p8l1cc.cloudfront.net/hearthstone/3836521ec48b25a14c01c45504987a31ba0abb038e742477efc09ebc56025920.png", "imageGold": "", "flavorText": "\"My ultimate is rea- ah, errr, I mean, I have enough Mana.\"", "cropImage": "https://d15f34w2p8l1cc.cloudfront.net/hearthstone/e9cd6f9700d6962bd4cb94055a14d903929a88eff553d20f77b1048b9b0b9174.png", "keywordIds": [12], "isZilliaxFunctionalModule": false, "isZilliaxCosmeticModule": false}, {"id": 91989, "collectible": 1, "slug": "91989-hipster", "classId": 12, "multiClassIds": [], "cardTypeId": 4, "cardSetId": 1809, "rarityId": 1, "artistName": "Ivan Fomin", "health": 3, "attack": 1, "manaCost": 2, "name": "Hipster", "text": "<b>Battlecry:</b> <b>Discover</b> a spell from your opponent's class that isn't in their deck.", "image": "https://d15f34w2p8l1cc.cloudfront.net/hearthstone/b72e2a32909e3fa03eb3b296e4a8089c91eecf96e760f87753b96faf73ea1820.png", "imageGold": "", "flavorText": "Oh, so you like Hearthstone? Name every spell.", "cropImage": "https://d15f34w2p8l1cc.cloudfront.net/hearthstone/eeb9e01bcfa48e8f8c36fcb1ae90273942ac3758f21c1b76f9c8e1c62edbaae0.png", "keywordIds": [8, 21], "isZilliaxFunctionalModule": false, "isZilliaxCosmeticModule": false}, {"id": 98560, "collectible": 1, "slug": "98560-hodir-father-of-giants", "classId": 3, "multiClassIds": [], "cardTypeId": 4, "cardSetId": 1858, "rarityId": 5, "artistName": "Alex Horley Orlandelli", "health": 8, "attack": 8, "manaCost": 8, "name": "Hodir, Father of Giants", "text": "<b>Battlecry:</b> Set the stats of the next three minions you play to 8/8.", "image": "https://d15f34w2p8l1cc.cloudfront.net/hearthstone/3638e77c275185652dd03f23ec59dee737c478c34c48501d9c2186050d0d0b87.png", "imageGold": "", "flavorText": "Giant ladies, this one's a Keeper.", "cropImage": "https://d15f34w2p8l1cc.cloudfront.net/hearthstone/f297e9e6bc56970b37d0c90b59044162fce7b48680c0b0a18f5c9ba9595c7148.png", "keywordIds": [8], "isZilliaxFunctionalModule": false, "isZilliaxCosmeticModule": false}, {"id": 94735, "collectible": 1, "slug": "94735-hollow-hound", "classId": 3, "multiClassIds": [1, 3], "minionTypeId": 11, "multiTypeIds": [20], "cardTypeId": 4, "cardSetId": 1809, "rarityId": 1, "artistName": "Slawomir Maniak", "health": 4, "attack": 3, "manaCost": 6, "name": "Hollow Hound", "text": "<b>Lifesteal</b>, <b>Rush</b> Also damages minions next to whomever this attacks.", "image": "https://d15f34w2p8l1cc.cloudfront.net/hearthstone/e75ebffb9d9aa9a46417b3ff5ddce36138cdd2b2201893755b4dc2d92a53b973.png", "imageGold": "", "flavorText": "Uh oh, the hollow hound is coming out of its cage! Don't worry though, it's doing just fine.", "cropImage": "https://d15f34w2p8l1cc.cloudfront.net/hearthstone/ec0e2176785a465dbc8067a9204b826eb3e70bdb15ff58b770fba3930050d0f6.png", "keywordIds": [38, 53], "isZilliaxFunctionalModule": false, "isZilliaxCosmeticModule": false}, {"id": 90671, "collectible": 1, "slug": "90671-holotechnician", "classId": 4, "multiClassIds": [], "cardTypeId": 4, "cardSetId": 1809, "rarityId": 4, "artistName": "Mooncolony ", "health": 4, "attack": 3, "manaCost": 3, "name": "Holotechnician", "text": "After ANY minion takes exactly 1 damage, destroy it.", "image": "https://d15f34w2p8l1cc.cloudfront.net/hearthstone/d1f7196ef860b4924c85c9e44eedc308c1b4bbd4b5137d6a9a1406b5ac160633.png", "imageGold": "", "flavorText": "Ironically, operating the spotlight comes with very little recognition.", "cropImage": "https://d15f34w2p8l1cc.cloudfront.net/hearthstone/f484422694b5550d3f89199850052954cddd9b3d3cda00eed46d301e628e4a2b.png", "isZilliaxFunctionalModule": false, "isZilliaxCosmeticModule": false}, {"id": 100118, "collectible": 1, "slug": "100118-holy-cowboy", "classId": 5, "multiClassIds": [], "cardTypeId": 4, "cardSetId": 1892, "rarityId": 1, "artistName": "Vlad Botos", "health": 3, "attack": 4, "manaCost": 3, "name": "Holy Cowboy", "text": "<b>Battlecry:</b> Your next Holy spell costs (2) less.", "image": "https://d15f34w2p8l1cc.cloudfront.net/hearthstone/f3bcda689c2679f255904443f4be79d4f86c871d20da758c803aa90c247b061a.png", "imageGold": "", "flavorText": "Wait, but\u2026 Isn't he more of a 'holy kodoboy'?", "cropImage": "https://d15f34w2p8l1cc.cloudfront.net/hearthstone/a6db00aa1263b5e7d8f01a97ffeacebc5107a0fde3fef4f29c85d66ad5fd2e09.png", "keywordIds": [8], "isZilliaxFunctionalModule": false, "isZilliaxCosmeticModule": false}, {"id": 105556, "collectible": 1, "slug": "105556-holy-glowsticks", "classId": 5, "multiClassIds": [], "spellSchoolId": 5, "cardTypeId": 5, "cardSetId": 1897, "rarityId": 1, "artistName": "Vika Yarova", "manaCost": 4, "name": "Holy Glowsticks", "text": "<b>Lifesteal</b> Deal 4 damage. Costs (1) if you've cast a Holy spell this turn.", "image": "https://d15f34w2p8l1cc.cloudfront.net/hearthstone/562e4d4ec05354896f6a5e7ce20eb439991c68fc64728983c91c9de5fa1546d5.png", "imageGold": "", "flavorText": "Somewhere there's a Naaru missing a couple of shards.", "cropImage": "https://d15f34w2p8l1cc.cloudfront.net/hearthstone/82ed6826447bb4cbcf70717d2ee2751c4131dd53ec6d545e5c353cce4452bbb5.png", "keywordIds": [38], "isZilliaxFunctionalModule": false, "isZilliaxCosmeticModule": false}, {"id": 69508, "collectible": 1, "slug": "69508-holy-nova", "classId": 6, "multiClassIds": [], "spellSchoolId": 5, "cardTypeId": 5, "cardSetId": 1637, "rarityId": 1, "artistName": "Luca Zontini", "manaCost": 3, "name": "Holy Nova", "text": "Deal 2 damage to all enemy minions. Restore 2 Health to all friendly characters.", "image": "https://d15f34w2p8l1cc.cloudfront.net/hearthstone/827424ff9a1aaa09940d79f36c1880e35bf79fe2e0c7321fc7196936aefdad64.png", "imageGold": "", "flavorText": "If the Holy Light forsakes you, good luck casting this spell. Also, you're probably a jerk.", "cropImage": "https://d15f34w2p8l1cc.cloudfront.net/hearthstone/687be88c7ac995fc525f78da24bb61d32ebbe1b31bd264217509393cf0202f8e.png", "copyOfCardId": 841, "isZilliaxFunctionalModule": false, "isZilliaxCosmeticModule": false}, {"id": 69509, "collectible": 1, "slug": "69509-holy-smite", "classId": 6, "multiClassIds": [], "spellSchoolId": 5, "cardTypeId": 5, "cardSetId": 1637, "rarityId": 1, "artistName": "Steve Ellis", "manaCost": 1, "name": "Holy Smite", "text": "Deal 3 damage to a minion.", "image": "https://d15f34w2p8l1cc.cloudfront.net/hearthstone/85d84e56feceb3bc57f8d573a1cc53cee3eba443dcf868885f1ff5ffc5b37b53.png", "imageGold": "", "flavorText": "It doesn't matter how pious you are. Everyone needs a good smiting now and again.", "cropImage": "https://d15f34w2p8l1cc.cloudfront.net/hearthstone/8a768f73ec6d919f924981a4f1a4ae0d5b8a8f9d00fe55c32efb82523753ee31.png", "copyOfCardId": 279, "isZilliaxFunctionalModule": false, "isZilliaxCosmeticModule": false}], "cardCount": 1034, "pageCount": 21, "page": 9}